ejercicio 4/ejercicio4.v
//Diseña un flip-flop tipo D con reloj síncrono y señal de reset asíncrono activo alto. El flip-flop debe
//almacenar el valor de la entrada D en el flanco positivo del reloj.
module ejercicio4(input wire clk, input wire d, input wire reset, output reg q);
    always @(posedge clk or posedge reset) begin
        if (reset) 
            begin
                q <= 1'b0;      // reset asíncrono: Q -> 0
            end 
        else begin
            q <= d;         // en flanco positivo de clk: capturar D
        end
    end
endmodule

HDL/ejercicio 4/ejercicio4_tb.v
`timescale 1ns / 1ps // 1 Nanosegundo / 1 Picosegundo
`include "ejercicio4.v"

// Testbench
module ejercicio4_tb;

// Declaración de las señales de entrada y de salida
reg clk;    
reg d;      
reg reset;  
wire q;  

// Instanciación del Multiplexor
ejercicio4 uut (
    .clk(clk), // Entrada de reloj
    .d(d), // Entrada d
    .reset(reset), // Entrada de reseteo
    .q(q) // Salida
);

// Generador de reloj
initial begin
    clk = 0;
    forever #5 clk = ~clk; // Periodo de 10ns
end

// Generaciòn de combinaciones para las entradas
initial begin
    $dumpfile("ejercicio4_tb.vcd");
    $dumpvars(0, ejercicio4_tb);

    // Mostrar Cabecera 
    $display ("Time | clk | d | reset | q");
    $display ("--------------------------------");

    // Aplicación de las combinaciones
    //Caso 1
    clk = 0; d = 0; reset = 0; #10;  // Espera 10 unidades de tiempo
    $display ("%0t  | %b | %b | %b | %b", $time, clk, d, reset, q);

    //Caso 2
    clk = 0; d = 0; reset = 1; #10;  // Espera 10 unidades de tiempo
    $display ("%0t  | %b | %b | %b | %b", $time, clk, d, reset, q);

    //Caso 3
    clk = 0; d =1; reset = 0; #10;  // Espera 10 unidades de tiempo
    $display ("%0t  | %b | %b | %b | %b", $time, clk, d, reset, q);

    //Caso 4
    clk = 0; d = 1; reset = 1; #10;  // Espera 10 unidades de tiempo
    $display ("%0t  | %b | %b | %b | %b", $time, clk, d, reset, q);

    //Caso 5
    clk = 1; d = 0; reset = 0; #10;  // Espera 10 unidades de tiempo
    $display ("%0t  | %b | %b | %b | %b", $time, clk, d, reset, q);

    //Caso 6
    clk = 1; d = 0; reset = 1; #10;  // Espera 10 unidades de tiempo
    $display ("%0t  | %b | %b | %b | %b", $time, clk, d, reset, q);

    //Caso 7
    clk = 1; d = 1; reset = 0; #10;  // Espera 10 unidades de tiempo
    $display ("%0t  | %b | %b | %b | %b", $time, clk, d, reset, q);

    //Caso 8
    clk = 1; d = 1; reset = 1; #10;  // Espera 10 unidades de tiempo
    $display ("%0t  | %b | %b | %b | %b", $time, clk, d, reset, q);

    $stop; // Detener la simulación
end
endmodule

ejercicio 4/ejercicio4_tb.vcd
$date
	Tue Aug 12 18:20:47 2025
$end
$version
	Icarus Verilog
$end
$timescale
	1ps
$end
$scope module ejercicio4_tb $end
$var wire 1 ! q $end
$var reg 1 " clk $end
$var reg 1 # d $end
$var reg 1 $ reset $end
$scope module uut $end
$var wire 1 " clk $end
$var wire 1 # d $end
$var wire 1 $ reset $end
$var reg 1 ! q $end
$upscope $end
$upscope $end
$enddefinitions $end
$comment Show the parameter values. $end
$dumpall
$end
#0
$dumpvars
0$
0#
0"
x!
$end
#5000
0!
1"
#10000
1$
1"
#15000
0"
#20000
1!
1"
0$
1#
#25000
0"
#30000
0!
1"
1$
#35000
0"
#40000
0$
0#
0"
#45000
1"
#50000
0"
1$
#55000
1"
#60000
0"
0$
1#
#65000
1!
1"
#70000
0!
0"
1$
