ejercicio 2/ejercicio2.v
// Diseña un registro de desplazamiento de 4 bits con entrada serial serial_in, señal de reloj clk, y
// salida en paralelo q[3:0]. En cada flanco positivo de clk debe desplazarse el dato serial hacia la
// derecha.
module ejercicio2(input wire clk,input wire serial_in,output reg [3:0] q);

    always @(posedge clk) begin
        q <= {serial_in, q[3:1]}; // desplaza a la derecha, entra serial_in en MSB
    end
endmodule

HDL/ejercicio 2/ejercicio2_tb.v
`timescale 1ns / 1ps // 1 Nanosegundo / 1 Picosegundo
`include "ejercicio2.v"

// Testbench
module ejercicio2_tb;

// Declaración de las señales de entrada y de salida
reg clk; // Entrada A
reg serial_in; // Entrada B
wire [3:0] q; // Salida

// Instanciación del módulo Shift_register
ejercicio2 uut (
    .clk(clk), // Conecta clk al módulo
    .serial_in(serial_in), // Conecta serial_in al módulo
    .q(q) // Conecta q al módulo
);


// Generaciòn de combinaciones para las entradas
initial begin
    $dumpfile("ejercicio2_tb.vcd");
    $dumpvars(0, ejercicio2_tb);

    // Mostrar Cabecera 
    $display ("Time | Serial_in | clk | Q");
    $display ("------------------------------");

    // Aplicación de las combinaciones
    serial_in = 0; clk = 0; #10; // Espera 10 unidades de tiempo
    $display ("%0t  | %b | %b |  %b ", $time, serial_in, clk, q);

    serial_in = 0; clk = 1; #10; // Espera 10 unidades de tiempo
    $display ("%0t  | %b | %b |  %b ", $time, serial_in, clk, q);

    serial_in = 1; clk = 0; #10; // Espera 10 unidades de tiempo
    $display ("%0t  | %b | %b |  %b ", $time, serial_in, clk, q);

    serial_in = 1; clk = 1; #10; // Espera 10 unidades de tiempo
    $display ("%0t  | %b | %b |  %b ", $time, serial_in, clk, q);

    serial_in = 0; clk = 0; #10; // Espera 10 unidades de tiempo
    $display ("%0t  | %b | %b |  %b ", $time, serial_in, clk, q);

    serial_in = 0; clk = 1; #10; // Espera 10 unidades de tiempo
    $display ("%0t  | %b | %b |  %b ", $time, serial_in, clk, q);

    serial_in = 1; clk = 0; #10; // Espera 10 unidades de tiempo
    $display ("%0t  | %b | %b |  %b ", $time, serial_in, clk, q);

    serial_in = 1; clk = 1; #10; // Espera 10 unidades de tiempo
    $display ("%0t  | %b | %b |  %b ", $time, serial_in, clk, q);

    serial_in = 0; clk = 0; #10; // Espera 10 unidades de tiempo
    $display ("%0t  | %b | %b |  %b ", $time, serial_in, clk, q);
    

    $stop; // Detener la simulación
end
endmodule

ejercicio 2/ejercicio2_tb.vcd
$date
	Mon Aug 11 18:44:31 2025
$end
$version
	Icarus Verilog
$end
$timescale
	1ps
$end
$scope module ejercicio2_tb $end
$var wire 4 ! q [3:0] $end
$var reg 1 " clk $end
$var reg 1 # serial_in $end
$scope module uut $end
$var wire 1 " clk $end
$var wire 1 # serial_in $end
$var reg 4 $ q [3:0] $end
$upscope $end
$upscope $end
$enddefinitions $end
$comment Show the parameter values. $end
$dumpall
$end
#0
$dumpvars
bx $
0#
0"
bx !
$end
#10000
b0xxx !
b0xxx $
1"
#20000
0"
1#
#30000
b10xx !
b10xx $
1"
#40000
0"
0#
#50000
b10x !
b10x $
1"
#60000
0"
1#
#70000
b1010 !
b1010 $
1"
#80000
0"
0#
