HDL/ejercicio 1/ejercicio1.v
//Diseñe un módulo en Verilog que implemente un sumador completo de un bit con entradas a,b y
//cin(carry in), y salidas sum y cout (carry out). Describir y simular con Icarus Verilog 
module ejercicio1 ( input a , input b , input cin , output sum , output co ) ;
assign sum = a ^ b ^ cin ;
assign co = ( a & b ) | cin & ( a ^ b ) ;
endmodule

HDL/ejercicio 1/ejercicio1_tb.v
`timescale 1ns / 1ps // 1 Nanosegundo / 1 Picosegundo
`include "ejercicio1.v"

// Testbench
module ejercicio1_tb;

// Declaración de las señales de entrada y de salida
reg a; // Entrada A
reg b; // Entrada B
reg cin;
wire sum; // Salida sum
wire co;

// Instanciación del módulo or_gate
ejercicio1 uut (
    .a(a), // Conecta A al módulo
    .b(b), // Conecta B al módulo
    .cin(cin), // Conecta cin al módulo
    .sum(sum),
    .co(co)
);

// Generaciòn de combinaciones para las entradas
initial begin
    $dumpfile("ejercicio1_tb.vcd");
    $dumpvars(0, ejercicio1_tb);

    // Mostrar Cabecera 
    $display ("Time | A | B | Cin | Sum | Co");
    $display ("------------------------------");

    // Aplicación de las combinaciones
    a = 0; b = 0; cin = 0; #10; // Espera 10 unidades de tiempo
    $display ("%0t  | %b | %b |  %b  |  %b  |  %b ", $time, a, b, cin, sum, co);

    a = 0; b = 1; cin = 0; #10; // Espera 10 unidades de tiempo
    $display ("%0t  | %b | %b |  %b  |  %b  |  %b ", $time, a, b, cin, sum, co);

    a = 1; b = 0; cin = 0; #10; // Espera 10 unidades de tiempo
    $display ("%0t  | %b | %b |  %b  |  %b  |  %b ", $time, a, b, cin, sum, co);

    a = 1; b = 1; cin = 0; #10; // Espera 10 unidades de tiempo
    $display ("%0t  | %b | %b |  %b  |  %b  |  %b ", $time, a, b, cin, sum, co);

    a = 0; b = 0; cin = 1; #10; // Espera 10 unidades de tiempo
    $display ("%0t  | %b | %b |  %b  |  %b  |  %b ", $time, a, b, cin, sum, co);

    a = 0; b = 1; cin = 1; #10; // Espera 10 unidades de tiempo
    $display ("%0t  | %b | %b |  %b  |  %b  |  %b ", $time, a, b, cin, sum, co);

    a = 1; b = 0; cin = 1; #10; // Espera 10 unidades de tiempo
    $display ("%0t  | %b | %b |  %b  |  %b  |  %b ", $time, a, b, cin, sum, co);

    a = 1; b = 1; cin = 1; #10; // Espera 10 unidades de tiempo
    $display ("%0t  | %b | %b |  %b  |  %b  |  %b ", $time, a, b, cin, sum, co);

    $stop; // Detener la simulación
end
endmodule

ejercicio 1/ejercicio1_tb.vcd
$date
	Mon Aug 11 10:58:04 2025
$end
$version
	Icarus Verilog
$end
$timescale
	1ps
$end
$scope module ejercicio1_tb $end
$var wire 1 ! sum $end
$var wire 1 " co $end
$var reg 1 # a $end
$var reg 1 $ b $end
$var reg 1 % cin $end
$scope module uut $end
$var wire 1 # a $end
$var wire 1 $ b $end
$var wire 1 % cin $end
$var wire 1 " co $end
$var wire 1 ! sum $end
$upscope $end
$upscope $end
$enddefinitions $end
$comment Show the parameter values. $end
$dumpall
$end
#0
$dumpvars
0%
0$
0#
0"
0!
$end
#10000
1!
1$
#20000
0$
1#
#30000
0!
1"
1$
#40000
0"
1!
1%
0$
0#
#50000
1"
0!
1$
#60000
0$
1#
#70000
1!
1$
